image_viewer_kit/__init__.py
image_viewer_kit/viewer.py
interactive-viewer-TEST/__init__.py
interactive-viewer-TEST/viewer.py
interactive_kit/__init__.py
interactive_kit/imageviewer.py
interactive_kit/imviewer.py
interactive_kit/signalviewer.py
interactive_kit/sigviewer.py
interactive_kit-0.1.6.dist-info/LICENSE
interactive_kit-0.1.6.dist-info/METADATA
interactive_kit-0.1.6.dist-info/WHEEL
interactive_kit-0.1.6.dist-info/top_level.txt
interactive_kit-0.1.6.dist-info/RECORD
