Metadata-Version: 2.1
Name: interactive-kit
Version: 0.1.6
Summary: Interactive viewer for signal processing, image processing, and machine learning
Home-page: https://github.com/Biomedical-Imaging-Group/interactive-kit
Author: Alejandro Noguerón
Author-email: alex.noguerona@gmail.com
License: UNKNOWN
Project-URL: Bug Tracker, https://github.com/Biomedical-Imaging-Group/IPLabImageViewer/issues
Platform: UNKNOWN
Classifier: Operating System :: OS Independent
Classifier: Development Status :: 5 - Production/Stable
Classifier: Programming Language :: Python :: 3.7
Classifier: License :: OSI Approved :: MIT License
Requires-Python: >=3.6
License-File: LICENSE
Requires-Dist: numpy
Requires-Dist: matplotlib
Requires-Dist: jupyter
Requires-Dist: ipympl
Requires-Dist: ipywidgets
Requires-Dist: opencv-python
